ilivalidator/__init__.py
ilivalidator/ilivalidator.py
ilivalidator/lib_ext/graal_isolate.h
ilivalidator/lib_ext/graal_isolate_dynamic.h
ilivalidator/lib_ext/libilivalidator.dll
ilivalidator/lib_ext/libilivalidator.h
ilivalidator/lib_ext/libilivalidator.lib
ilivalidator/lib_ext/libilivalidator_dynamic.h
ilivalidator/tests/__init__.py
ilivalidator/tests/test_ilivalidator.py
ilivalidator-0.0.4.dist-info/LICENSE
ilivalidator-0.0.4.dist-info/METADATA
ilivalidator-0.0.4.dist-info/WHEEL
ilivalidator-0.0.4.dist-info/top_level.txt
ilivalidator-0.0.4.dist-info/RECORD
