Metadata-Version: 2.1
Name: ilivalidator
Version: 0.0.4
Summary: Python package for ilivalidator.
Home-page: https://github.com/pylitools/ilivalidator
Author: Stefan Ziegler
Author-email: edi.gonzales@gmail.com
License: MIT license
Keywords: ilivalidator,interlis
Classifier: Programming Language :: Python :: 3
Classifier: License :: OSI Approved :: MIT License
Classifier: Operating System :: POSIX :: Linux
Classifier: Operating System :: Microsoft :: Windows
Classifier: Operating System :: MacOS
Requires-Python: >=3.8
License-File: LICENSE
Requires-Dist: importlib-resources
Provides-Extra: test
Requires-Dist: pytest ; extra == 'test'
